.gitignore
CHANGES.txt
MANIFEST.in
README.rst
nose_xunitmp.py
setup.py
nose_xunitmp.egg-info/PKG-INFO
nose_xunitmp.egg-info/SOURCES.txt
nose_xunitmp.egg-info/dependency_links.txt
nose_xunitmp.egg-info/entry_points.txt
nose_xunitmp.egg-info/requires.txt
nose_xunitmp.egg-info/top_level.txt
nose_xunitmp.egg-info/zip-safe