Metadata-Version: 1.1
Name: nose-xunitmp
Version: 0.4.0
Summary: Xunit output when running multiprocess tests using nose
Home-page: UNKNOWN
Author: Ignas Mikalajunas
Author-email: ignas@uber.com
License: MIT
Keywords: nosetest xunit multiprocessing
Platform: UNKNOWN
Classifier: Development Status :: 4 - Beta
Classifier: Intended Audience :: Developers
Classifier: License :: OSI Approved :: MIT License
Classifier: Operating System :: OS Independent
Classifier: Programming Language :: Python
Classifier: Topic :: Software Development :: Testing
